[{"time_diff": 0.0, "position": [770, 706], "left_click": false, "right_click": false, "scroll": 0}, {"time_diff": 0.05530405044555664, "position": [770, 706], "left_click": false, "right_click": false, "scroll": 0}, {"time_diff": 0.0631096363067627, "position": [770, 706], "left_click": false, "right_click": false, "scroll": 0}, {"time_diff": 0.06194114685058594, "position": [770, 706], "left_click": false, "right_click": false, "scroll": 0}, {"time_diff": 0.06162858009338379, "position": [770, 706], "left_click": false, "right_click": false, "scroll": 0}, {"time_diff": 0.06267738342285156, "position": [770, 706], "left_click": false, "right_click": false, "scroll": 0}, {"time_diff": 0.06298375129699707, "position": [770, 706], "left_click": false, "right_click": false, "scroll": 0}, {"time_diff": 0.0650320053100586, "position": [770, 706], "left_click": false, "right_click": false, "scroll": 0}, {"time_diff": 0.05927252769470215, "position": [770, 706], "left_click": false, "right_click": false, "scroll": 0}, {"time_diff": 0.06279969215393066, "position": [770, 706], "left_click": false, "right_click": false, "scroll": 0}, {"time_diff": 0.06288385391235352, "position": [770, 706], "left_click": false, "right_click": false, "scroll": 0}, {"time_diff": 0.06424236297607422, "position": [763, 686], "left_click": false, "right_click": false, "scroll": -20}, {"time_diff": 0.05887269973754883, "position": [753, 674], "left_click": false, "right_click": false, "scroll": -12}, {"time_diff": 0.062316179275512695, "position": [750, 670], "left_click": false, "right_click": false, "scroll": -4}, {"time_diff": 0.06253218650817871, "position": [749, 669], "left_click": false, "right_click": false, "scroll": -1}, {"time_diff": 0.06229567527770996, "position": [716, 617], "left_click": false, "right_click": false, "scroll": -52}, {"time_diff": 0.06153440475463867, "position": [589, 511], "left_click": false, "right_click": false, "scroll": -106}, {"time_diff": 0.06305766105651855, "position": [371, 337], "left_click": false, "right_click": false, "scroll": -174}, {"time_diff": 0.0625312328338623, "position": [229, 221], "left_click": false, "right_click": false, "scroll": -116}, {"time_diff": 0.06168985366821289, "position": [195, 182], "left_click": false, "right_click": false, "scroll": -39}, {"time_diff": 0.06298136711120605, "position": [125, 127], "left_click": false, "right_click": false, "scroll": -55}, {"time_diff": 0.06297516822814941, "position": [90, 109], "left_click": false, "right_click": false, "scroll": -18}, {"time_diff": 0.06282758712768555, "position": [37, 86], "left_click": false, "right_click": false, "scroll": -23}, {"time_diff": 0.05781078338623047, "position": [13, 70], "left_click": false, "right_click": false, "scroll": -16}, {"time_diff": 0.06182384490966797, "position": [9, 65], "left_click": false, "right_click": false, "scroll": -5}, {"time_diff": 0.06404805183410645, "position": [9, 65], "left_click": false, "right_click": false, "scroll": 0}, {"time_diff": 0.06201910972595215, "position": [9, 65], "left_click": false, "right_click": false, "scroll": 0}, {"time_diff": 0.06210017204284668, "position": [9, 65], "left_click": false, "right_click": false, "scroll": 0}, {"time_diff": 0.061200857162475586, "position": [9, 65], "left_click": true, "right_click": false, "scroll": 0}, {"time_diff": 0.06360554695129395, "position": [9, 65], "left_click": true, "right_click": false, "scroll": 0, "double_click": true}, {"time_diff": 0.06180739402770996, "position": [9, 65], "left_click": false, "right_click": false, "scroll": 0}, {"time_diff": 0.062390804290771484, "position": [9, 65], "left_click": false, "right_click": false, "scroll": 0}, {"time_diff": 0.062046051025390625, "position": [9, 65], "left_click": false, "right_click": false, "scroll": 0}, {"time_diff": 0.06209731101989746, "position": [9, 65], "left_click": false, "right_click": false, "scroll": 0}, {"time_diff": 0.06369924545288086, "position": [9, 65], "left_click": false, "right_click": false, "scroll": 0}, {"time_diff": 0.06319522857666016, "position": [9, 65], "left_click": false, "right_click": false, "scroll": 0}, {"time_diff": 0.06096816062927246, "position": [9, 65], "left_click": false, "right_click": false, "scroll": 0}, {"time_diff": 0.061208248138427734, "position": [9, 65], "left_click": false, "right_click": false, "scroll": 0}, {"time_diff": 0.06284427642822266, "position": [9, 65], "left_click": false, "right_click": false, "scroll": 0}, {"time_diff": 0.06875205039978027, "position": [9, 65], "left_click": false, "right_click": false, "scroll": 0}, {"time_diff": 0.05569195747375488, "position": [17, 63], "left_click": false, "right_click": false, "scroll": -2}, {"time_diff": 0.06158566474914551, "position": [95, 91], "left_click": false, "right_click": false, "scroll": 28}, {"time_diff": 0.062273263931274414, "position": [181, 120], "left_click": false, "right_click": false, "scroll": 29}, {"time_diff": 0.06283235549926758, "position": [310, 185], "left_click": false, "right_click": false, "scroll": 65}, {"time_diff": 0.05398750305175781, "position": [465, 245], "left_click": false, "right_click": false, "scroll": 60}, {"time_diff": 0.06403160095214844, "position": [642, 319], "left_click": false, "right_click": false, "scroll": 74}, {"time_diff": 0.051343679428100586, "position": [770, 364], "left_click": false, "right_click": false, "scroll": 45}, {"time_diff": 0.0629878044128418, "position": [965, 430], "left_click": false, "right_click": false, "scroll": 66}, {"time_diff": 0.06307339668273926, "position": [1154, 502], "left_click": false, "right_click": false, "scroll": 72}, {"time_diff": 0.06382107734680176, "position": [1313, 563], "left_click": false, "right_click": false, "scroll": 61}, {"time_diff": 0.06310510635375977, "position": [1434, 617], "left_click": false, "right_click": false, "scroll": 54}, {"time_diff": 0.06201624870300293, "position": [1531, 671], "left_click": false, "right_click": false, "scroll": 54}, {"time_diff": 0.0620112419128418, "position": [1535, 719], "left_click": false, "right_click": false, "scroll": 48}, {"time_diff": 0.061598777770996094, "position": [1535, 775], "left_click": false, "right_click": false, "scroll": 56}, {"time_diff": 0.061884164810180664, "position": [1535, 830], "left_click": false, "right_click": false, "scroll": 55}, {"time_diff": 0.06257462501525879, "position": [1535, 863], "left_click": false, "right_click": false, "scroll": 33}, {"time_diff": 0.06165194511413574, "position": [1535, 863], "left_click": false, "right_click": false, "scroll": 0}, {"time_diff": 0.060742855072021484, "position": [1535, 863], "left_click": false, "right_click": false, "scroll": 0}, {"time_diff": 0.06142997741699219, "position": [1535, 863], "left_click": false, "right_click": false, "scroll": 0}, {"time_diff": 0.06263017654418945, "position": [1535, 863], "left_click": false, "right_click": false, "scroll": 0}, {"time_diff": 0.06342196464538574, "position": [1535, 863], "left_click": true, "right_click": false, "scroll": 0}, {"time_diff": 0.06212139129638672, "position": [1535, 863], "left_click": false, "right_click": false, "scroll": 0}, {"time_diff": 0.06198620796203613, "position": [1535, 863], "left_click": false, "right_click": false, "scroll": 0}, {"time_diff": 0.06153273582458496, "position": [1535, 863], "left_click": false, "right_click": false, "scroll": 0}, {"time_diff": 0.06220197677612305, "position": [1535, 863], "left_click": false, "right_click": false, "scroll": 0}, {"time_diff": 0.06294012069702148, "position": [1535, 863], "left_click": false, "right_click": false, "scroll": 0}, {"time_diff": 0.06272554397583008, "position": [1535, 863], "left_click": false, "right_click": false, "scroll": 0}, {"time_diff": 0.06278324127197266, "position": [1535, 863], "left_click": false, "right_click": false, "scroll": 0}, {"time_diff": 0.06298160552978516, "position": [1510, 845], "left_click": false, "right_click": false, "scroll": -18}, {"time_diff": 0.06274724006652832, "position": [1402, 780], "left_click": false, "right_click": false, "scroll": -65}, {"time_diff": 0.06212592124938965, "position": [1293, 714], "left_click": false, "right_click": false, "scroll": -66}, {"time_diff": 0.0633399486541748, "position": [1146, 646], "left_click": false, "right_click": false, "scroll": -68}, {"time_diff": 0.06253361701965332, "position": [977, 582], "left_click": false, "right_click": false, "scroll": -64}, {"time_diff": 0.06332063674926758, "position": [802, 518], "left_click": false, "right_click": false, "scroll": -64}, {"time_diff": 0.06277346611022949, "position": [617, 473], "left_click": false, "right_click": false, "scroll": -45}, {"time_diff": 0.06198453903198242, "position": [432, 442], "left_click": false, "right_click": false, "scroll": -31}, {"time_diff": 0.06538701057434082, "position": [277, 437], "left_click": false, "right_click": false, "scroll": -5}, {"time_diff": 0.06260991096496582, "position": [198, 443], "left_click": false, "right_click": false, "scroll": 6}, {"time_diff": 0.06174278259277344, "position": [117, 437], "left_click": false, "right_click": false, "scroll": -6}, {"time_diff": 0.06237602233886719, "position": [52, 434], "left_click": false, "right_click": false, "scroll": -3}, {"time_diff": 0.06320500373840332, "position": [22, 434], "left_click": false, "right_click": false, "scroll": 0}, {"time_diff": 0.05084657669067383, "position": [18, 434], "left_click": false, "right_click": false, "scroll": 0}, {"time_diff": 0.06231689453125, "position": [18, 434], "left_click": false, "right_click": false, "scroll": 0}, {"time_diff": 0.0630636215209961, "position": [18, 434], "left_click": false, "right_click": false, "scroll": 0}, {"time_diff": 0.06271886825561523, "position": [18, 434], "left_click": false, "right_click": false, "scroll": 0}, {"time_diff": 0.06217026710510254, "position": [18, 434], "left_click": false, "right_click": false, "scroll": 0}, {"time_diff": 0.05587196350097656, "position": [18, 434], "left_click": false, "right_click": false, "scroll": 0}, {"time_diff": 0.06212496757507324, "position": [18, 434], "left_click": false, "right_click": false, "scroll": 0}, {"time_diff": 0.05270719528198242, "position": [18, 434], "left_click": false, "right_click": false, "scroll": 0}, {"time_diff": 0.062236785888671875, "position": [18, 434], "left_click": false, "right_click": false, "scroll": 0}, {"time_diff": 0.06203770637512207, "position": [18, 434], "left_click": false, "right_click": false, "scroll": 0}, {"time_diff": 0.062378883361816406, "position": [18, 434], "left_click": true, "right_click": false, "scroll": 0}, {"time_diff": 0.050199031829833984, "position": [18, 434], "left_click": true, "right_click": false, "scroll": 0, "double_click": true}, {"time_diff": 0.06321430206298828, "position": [18, 434], "left_click": false, "right_click": false, "scroll": 0}, {"time_diff": 0.06157565116882324, "position": [18, 434], "left_click": false, "right_click": false, "scroll": 0}, {"time_diff": 0.06220722198486328, "position": [18, 434], "left_click": false, "right_click": false, "scroll": 0}, {"time_diff": 0.06397461891174316, "position": [18, 434], "left_click": false, "right_click": false, "scroll": 0}, {"time_diff": 0.06004190444946289, "position": [18, 434], "left_click": false, "right_click": false, "scroll": 0}, {"time_diff": 0.06087827682495117, "position": [18, 434], "left_click": false, "right_click": false, "scroll": 0}, {"time_diff": 0.06288528442382812, "position": [18, 434], "left_click": false, "right_click": false, "scroll": 0}, {"time_diff": 0.06328177452087402, "position": [18, 434], "left_click": false, "right_click": false, "scroll": 0}, {"time_diff": 0.06183910369873047, "position": [18, 434], "left_click": false, "right_click": false, "scroll": 0}, {"time_diff": 0.06206989288330078, "position": [18, 434], "left_click": false, "right_click": false, "scroll": 0}, {"time_diff": 0.06247353553771973, "position": [18, 434], "left_click": false, "right_click": false, "scroll": 0}, {"time_diff": 0.06720805168151855, "position": [18, 434], "left_click": false, "right_click": false, "scroll": 0}, {"time_diff": 0.05730175971984863, "position": [41, 418], "left_click": false, "right_click": false, "scroll": -16}, {"time_diff": 0.060672760009765625, "position": [98, 396], "left_click": false, "right_click": false, "scroll": -22}, {"time_diff": 0.06338930130004883, "position": [169, 374], "left_click": false, "right_click": false, "scroll": -22}, {"time_diff": 0.061922550201416016, "position": [274, 354], "left_click": false, "right_click": false, "scroll": -20}, {"time_diff": 0.05819392204284668, "position": [398, 350], "left_click": false, "right_click": false, "scroll": -4}, {"time_diff": 0.06298494338989258, "position": [516, 344], "left_click": false, "right_click": false, "scroll": -6}, {"time_diff": 0.06269001960754395, "position": [625, 344], "left_click": false, "right_click": false, "scroll": 0}, {"time_diff": 0.06250190734863281, "position": [745, 346], "left_click": false, "right_click": false, "scroll": 2}, {"time_diff": 0.06107735633850098, "position": [833, 351], "left_click": false, "right_click": false, "scroll": 5}, {"time_diff": 0.06209421157836914, "position": [921, 354], "left_click": false, "right_click": false, "scroll": 3}, {"time_diff": 0.06298112869262695, "position": [950, 354], "left_click": false, "right_click": false, "scroll": 0}, {"time_diff": 0.0634317398071289, "position": [950, 354], "left_click": false, "right_click": false, "scroll": 0}, {"time_diff": 0.06207728385925293, "position": [950, 354], "left_click": false, "right_click": false, "scroll": 0}, {"time_diff": 0.062170982360839844, "position": [950, 354], "left_click": false, "right_click": false, "scroll": 0}, {"time_diff": 0.06189727783203125, "position": [950, 354], "left_click": true, "right_click": false, "scroll": 0}, {"time_diff": 0.061379432678222656, "position": [950, 354], "left_click": false, "right_click": false, "scroll": 0}, {"time_diff": 0.06260013580322266, "position": [950, 354], "left_click": false, "right_click": false, "scroll": 0}, {"time_diff": 0.06504988670349121, "position": [950, 354], "left_click": false, "right_click": false, "scroll": 0}, {"time_diff": 0.061956167221069336, "position": [950, 354], "left_click": false, "right_click": false, "scroll": 0}, {"time_diff": 0.06275558471679688, "position": [950, 354], "left_click": false, "right_click": false, "scroll": 0}, {"time_diff": 0.06361269950866699, "position": [950, 354], "left_click": false, "right_click": false, "scroll": 0}, {"time_diff": 0.05879712104797363, "position": [950, 354], "left_click": false, "right_click": false, "scroll": 0}, {"time_diff": 0.06195521354675293, "position": [950, 354], "left_click": false, "right_click": false, "scroll": 0}, {"time_diff": 0.06215023994445801, "position": [954, 354], "left_click": false, "right_click": false, "scroll": 0}, {"time_diff": 0.05586814880371094, "position": [979, 322], "left_click": false, "right_click": false, "scroll": -32}, {"time_diff": 0.06323671340942383, "position": [1015, 272], "left_click": false, "right_click": false, "scroll": -50}, {"time_diff": 0.06168365478515625, "position": [1060, 214], "left_click": false, "right_click": false, "scroll": -58}, {"time_diff": 0.0634615421295166, "position": [1095, 169], "left_click": false, "right_click": false, "scroll": -45}, {"time_diff": 0.06206822395324707, "position": [1105, 152], "left_click": false, "right_click": false, "scroll": -17}, {"time_diff": 0.062154531478881836, "position": [1113, 136], "left_click": false, "right_click": false, "scroll": -16}, {"time_diff": 0.06372904777526855, "position": [1123, 122], "left_click": false, "right_click": false, "scroll": -14}, {"time_diff": 0.062127113342285156, "position": [1130, 114], "left_click": false, "right_click": false, "scroll": -8}, {"time_diff": 0.05753588676452637, "position": [1138, 108], "left_click": false, "right_click": false, "scroll": -6}, {"time_diff": 0.061625003814697266, "position": [1138, 108], "left_click": false, "right_click": false, "scroll": 0}, {"time_diff": 0.06186676025390625, "position": [1138, 108], "left_click": true, "right_click": false, "scroll": 0}, {"time_diff": 0.0635077953338623, "position": [1138, 108], "left_click": false, "right_click": false, "scroll": 0}, {"time_diff": 0.05453848838806152, "position": [1138, 108], "left_click": false, "right_click": false, "scroll": 0}, {"time_diff": 0.06340146064758301, "position": [1138, 108], "left_click": false, "right_click": false, "scroll": 0}, {"time_diff": 0.062071800231933594, "position": [1062, 133], "left_click": false, "right_click": false, "scroll": 25}, {"time_diff": 0.06327438354492188, "position": [888, 246], "left_click": false, "right_click": false, "scroll": 113}, {"time_diff": 0.06360316276550293, "position": [790, 394], "left_click": false, "right_click": false, "scroll": 148}, {"time_diff": 0.058922529220581055, "position": [762, 519], "left_click": false, "right_click": false, "scroll": 125}, {"time_diff": 0.06265902519226074, "position": [736, 644], "left_click": false, "right_click": false, "scroll": 125}, {"time_diff": 0.062415122985839844, "position": [721, 699], "left_click": false, "right_click": false, "scroll": 55}, {"time_diff": 0.06480979919433594, "position": [713, 719], "left_click": false, "right_click": false, "scroll": 20}, {"time_diff": 0.059746742248535156, "position": [702, 735], "left_click": false, "right_click": false, "scroll": 16}, {"time_diff": 0.06281495094299316, "position": [692, 762], "left_click": false, "right_click": false, "scroll": 27}, {"time_diff": 0.06191277503967285, "position": [673, 791], "left_click": false, "right_click": false, "scroll": 29}, {"time_diff": 0.06384825706481934, "position": [657, 819], "left_click": false, "right_click": false, "scroll": 28}, {"time_diff": 0.06297183036804199, "position": [654, 827], "left_click": false, "right_click": false, "scroll": 8}, {"time_diff": 0.05958986282348633, "position": [653, 831], "left_click": false, "right_click": false, "scroll": 4}, {"time_diff": 0.06237936019897461, "position": [653, 833], "left_click": false, "right_click": false, "scroll": 2}, {"time_diff": 0.06235074996948242, "position": [653, 833], "left_click": false, "right_click": false, "scroll": 0}, {"time_diff": 0.06388354301452637, "position": [653, 833], "left_click": false, "right_click": false, "scroll": 0}, {"time_diff": 0.0549771785736084, "position": [653, 833], "left_click": false, "right_click": false, "scroll": 0}, {"time_diff": 0.05368828773498535, "position": [650, 835], "left_click": false, "right_click": false, "scroll": 2}, {"time_diff": 0.06964659690856934, "position": [634, 838], "left_click": false, "right_click": false, "scroll": 3}, {"time_diff": 0.05665874481201172, "position": [622, 840], "left_click": false, "right_click": false, "scroll": 2}, {"time_diff": 0.06933951377868652, "position": [614, 841], "left_click": false, "right_click": false, "scroll": 1}, {"time_diff": 0.061289310455322266, "position": [613, 841], "left_click": false, "right_click": false, "scroll": 0}, {"time_diff": 0.07517123222351074, "position": [613, 841], "left_click": false, "right_click": false, "scroll": 0}, {"time_diff": 0.059267282485961914, "position": [613, 841], "left_click": true, "right_click": false, "scroll": 0}, {"time_diff": 0.05393624305725098, "position": [613, 841], "left_click": true, "right_click": false, "scroll": 0, "double_click": true}, {"time_diff": 0.056693315505981445, "position": [613, 841], "left_click": false, "right_click": false, "scroll": 0}, {"time_diff": 0.05568408966064453, "position": [613, 841], "left_click": false, "right_click": false, "scroll": 0}, {"time_diff": 0.055075883865356445, "position": [613, 841], "left_click": false, "right_click": false, "scroll": 0}, {"time_diff": 0.06662845611572266, "position": [613, 841], "left_click": false, "right_click": false, "scroll": 0}, {"time_diff": 0.06081819534301758, "position": [613, 841], "left_click": false, "right_click": false, "scroll": 0}, {"time_diff": 0.05555319786071777, "position": [613, 841], "left_click": false, "right_click": false, "scroll": 0}, {"time_diff": 0.06138014793395996, "position": [613, 841], "left_click": false, "right_click": false, "scroll": 0}, {"time_diff": 0.061570167541503906, "position": [618, 817], "left_click": false, "right_click": false, "scroll": -24}, {"time_diff": 0.06140613555908203, "position": [632, 793], "left_click": false, "right_click": false, "scroll": -24}, {"time_diff": 0.06248617172241211, "position": [683, 762], "left_click": false, "right_click": false, "scroll": -31}, {"time_diff": 0.07104277610778809, "position": [741, 745], "left_click": false, "right_click": false, "scroll": -17}, {"time_diff": 0.0715639591217041, "position": [743, 744], "left_click": true, "right_click": false, "scroll": -1}, {"time_diff": 0.06349372863769531, "position": [743, 744], "left_click": false, "right_click": false, "scroll": 0}, {"time_diff": 0.06393837928771973, "position": [743, 744], "left_click": false, "right_click": false, "scroll": 0}, {"time_diff": 0.061601877212524414, "position": [743, 744], "left_click": false, "right_click": false, "scroll": 0}, {"time_diff": 0.06163978576660156, "position": [743, 744], "left_click": false, "right_click": false, "scroll": 0}]